asreviewcontrib/datatools/__init__.py
asreviewcontrib/datatools/compose.py
asreviewcontrib/datatools/convert.py
asreviewcontrib/datatools/dedup.py
asreviewcontrib/datatools/describe.py
asreviewcontrib/datatools/entrypoint.py
asreviewcontrib/datatools/sample.py
asreviewcontrib/datatools/snowball.py
asreviewcontrib/datatools/stack.py
asreview_datatools-1.4.dist-info/LICENSE
asreview_datatools-1.4.dist-info/METADATA
asreview_datatools-1.4.dist-info/WHEEL
asreview_datatools-1.4.dist-info/entry_points.txt
asreview_datatools-1.4.dist-info/top_level.txt
asreview_datatools-1.4.dist-info/RECORD
