Metadata-Version: 2.2
Name: asreview-datatools
Version: 1.4
Summary: Powerful command line tools for data handling in ASReview
Author-email: ASReview LAB developers <asreview@uu.nl>
License: MIT License
Project-URL: homepage, https://asreview.ai
Project-URL: repository, https://github.com/asreview/asreview-datatools
Project-URL: issues, https://github.com/asreview/asreview-datatools/issues
Classifier: Development Status :: 5 - Production/Stable
Classifier: License :: OSI Approved :: MIT License
Classifier: Programming Language :: Python :: 3.8
Classifier: Programming Language :: Python :: 3.9
Classifier: Programming Language :: Python :: 3.10
Classifier: Programming Language :: Python :: 3.11
Requires-Python: >=3.8
License-File: LICENSE
Requires-Dist: asreview<2,>=1.1
Requires-Dist: ftfy
Requires-Dist: nltk
Requires-Dist: pandas
Requires-Dist: pyalex
Requires-Dist: rich
Requires-Dist: tqdm
Provides-Extra: lint
Requires-Dist: ruff; extra == "lint"
Provides-Extra: test
Requires-Dist: pytest; extra == "test"
